gemma/__init__.py
gemma/gm/README.md
gemma/gm/__init__.py
gemma/gm/ckpts/__init__.py
gemma/gm/ckpts/_checkpoint.py
gemma/gm/ckpts/_compat.py
gemma/gm/ckpts/_lora.py
gemma/gm/ckpts/_paths.py
gemma/gm/ckpts/_policy.py
gemma/gm/ckpts/_quantization.py
gemma/gm/data/__init__.py
gemma/gm/data/_functional.py
gemma/gm/data/_parquet.py
gemma/gm/data/_tasks.py
gemma/gm/data/_transforms.py
gemma/gm/evals/__init__.py
gemma/gm/evals/_sample.py
gemma/gm/losses/__init__.py
gemma/gm/losses/_dpo.py
gemma/gm/losses/_npo.py
gemma/gm/math/__init__.py
gemma/gm/math/_misc.py
gemma/gm/math/_pos_utils.py
gemma/gm/math/_positional_embeddings.py
gemma/gm/nn/__init__.py
gemma/gm/nn/_config.py
gemma/gm/nn/_experimental.py
gemma/gm/nn/_gemma.py
gemma/gm/nn/_layers.py
gemma/gm/nn/_lora.py
gemma/gm/nn/_modules.py
gemma/gm/nn/_policy.py
gemma/gm/nn/_quantization.py
gemma/gm/nn/_transformer.py
gemma/gm/nn/_transformer_like.py
gemma/gm/nn/config.py
gemma/gm/nn/gemma3n/README.md
gemma/gm/nn/gemma3n/__init__.py
gemma/gm/nn/gemma3n/_config.py
gemma/gm/nn/gemma3n/_gemma3n.py
gemma/gm/nn/gemma3n/_layers.py
gemma/gm/nn/gemma3n/_modules.py
gemma/gm/nn/gemma3n/_transformer.py
gemma/gm/sharding/__init__.py
gemma/gm/testing/__init__.py
gemma/gm/testing/_dummy_model.py
gemma/gm/testing/_dummy_tokenizer.py
gemma/gm/testing/_fixtures.py
gemma/gm/text/__init__.py
gemma/gm/text/_chat_sampler.py
gemma/gm/text/_prefill.py
gemma/gm/text/_sampler.py
gemma/gm/text/_sampler_loop.py
gemma/gm/text/_sampling.py
gemma/gm/text/_template.py
gemma/gm/text/_tokenizer.py
gemma/gm/text/_tool_sampler.py
gemma/gm/text/_turn_utils.py
gemma/gm/tools/__init__.py
gemma/gm/tools/_calculator.py
gemma/gm/tools/_file_explorer.py
gemma/gm/tools/_manager.py
gemma/gm/tools/_offline_tool_search.py
gemma/gm/tools/_tools.py
gemma/gm/typing/__init__.py
gemma/gm/typing/_common.py
gemma/gm/utils/__init__.py
gemma/gm/utils/_attention_mask.py
gemma/gm/utils/_cache_helper.py
gemma/gm/utils/_dtype_params.py
gemma/gm/utils/_file_cache.py
gemma-3.3.0.dist-info/licenses/LICENSE
gemma-3.3.0.dist-info/WHEEL
gemma-3.3.0.dist-info/METADATA
gemma-3.3.0.dist-info/RECORD
