Metadata-Version: 2.4
Name: gemma
Version: 3.3.0
Summary: Gemma open-weight LLM library from Google DeepMind.
Keywords: 
Author-email: Alek Andreev <alekandreev@google.com>, Armand Joulin <ajoulin@google.com>, Cassidy Hardin <cassidyhardin@google.com>, Juliette Love <juliettelove@google.com>, Kathleen Kenealy <kkenealy@google.com>, Laurent Sifre <sifre@google.com>, Léonard Hussenot <hussenot@google.com>, Michelle Casbon <michellecasbon@google.com>, Mihir Sanjay Kale <mihirkale@google.com>, Morgane Riviere <mriviere@google.com>, Ravin Kumar <ravink@google.com>, Robert Dadashi <dadashi@google.com>, Shreya Pathak <sh
Requires-Python: >=3.11
Classifier: License :: OSI Approved :: Apache Software License
Classifier: Intended Audience :: Science/Research
License-File: LICENSE
Requires-Dist: absl-py
Requires-Dist: etils[edc, enp, epath, epy, etree]
Requires-Dist: einops
Requires-Dist: grain ; sys_platform != 'win32'
Requires-Dist: jax
Requires-Dist: jaxtyping
Requires-Dist: kauldron
Requires-Dist: flax
Requires-Dist: numpy
Requires-Dist: orbax-checkpoint
Requires-Dist: sentencepiece
Requires-Dist: treescope
Requires-Dist: pytest ; extra == "dev"
Requires-Dist: pytest-xdist ; extra == "dev"
Requires-Dist: pylint>=2.6.0 ; extra == "dev"
Requires-Dist: pyink ; extra == "dev"
Project-URL: changelog, https://github.com/google-deepmind/gemma/blob/main/CHANGELOG.md
Project-URL: homepage, https://gemma-llm.readthedocs.io/en/latest/
Project-URL: repository, https://github.com/google-deepmind/gemma
Provides-Extra: dev
